{
  "0.jpg": {
    "config_dict": {
      "steps": {
        "image_rotation": {
          "enabled": true,
          "parameters": {
            "rotation_angle": {
              "value": 247.0
            }
          }
        },
        "shadow_removal": {
          "enabled": true,
          "parameters": {
            "shadow_kernel_size": {
              "value": 20.0
            },
            "shadow_median_blur": {
              "value": 12.0
            }
          }
        },
        "color_clahe": {
          "enabled": true,
          "parameters": {
            "clahe_clip_limit": {
              "value": 3.0
            }
          }
        },
        "brightness_adjustment": {
          "enabled": true,
          "parameters": {
            "brightness_value": {
              "value": 28.0
            }
          }
        },
        "contrast_adjustment": {
          "enabled": true,
          "parameters": {
            "contrast_value": {
              "value": 0.7
            }
          }
        }
      }
    },
    "ocr_results": [
      {
        "text": "THE DIARV OFAVOUNG GIRL",
        "confidence": 0.8325477349256963
      },
      {
        "text": "ANNE FRANK:",
        "confidence": 0.9831285460249515
      }
    ],
    "score": 29.96301190956548
  },
  "1.jpg": {
    "config_dict": {
      "steps": {
        "image_rotation": {
          "enabled": true,
          "parameters": {
            "rotation_angle": {
              "value": 270.0
            }
          }
        },
        "shadow_removal": {
          "enabled": true,
          "parameters": {
            "shadow_kernel_size": {
              "value": 26.0
            },
            "shadow_median_blur": {
              "value": 13.0
            }
          }
        },
        "color_clahe": {
          "enabled": true,
          "parameters": {
            "clahe_clip_limit": {
              "value": 5.0
            }
          }
        },
        "brightness_adjustment": {
          "enabled": true,
          "parameters": {
            "brightness_value": {
              "value": 30.0
            }
          }
        },
        "contrast_adjustment": {
          "enabled": true,
          "parameters": {
            "contrast_value": {
              "value": 0.7
            }
          }
        }
      }
    },
    "ocr_results": [
      {
        "text": "THE FORESHADOWING",
        "confidence": 0.9719175238906922
      }
    ],
    "score": 16.52259790614177
  },
  "10.jpg": {
    "config_dict": {
      "steps": {
        "image_rotation": {
          "enabled": true,
          "parameters": {
            "rotation_angle": {
              "value": 148.0
            }
          }
        },
        "shadow_removal": {
          "enabled": true,
          "parameters": {
            "shadow_kernel_size": {
              "value": 11.0
            },
            "shadow_median_blur": {
              "value": 16.0
            }
          }
        },
        "color_clahe": {
          "enabled": true,
          "parameters": {
            "clahe_clip_limit": {
              "value": 1.9
            }
          }
        },
        "brightness_adjustment": {
          "enabled": true,
          "parameters": {
            "brightness_value": {
              "value": -6.0
            }
          }
        },
        "contrast_adjustment": {
          "enabled": true,
          "parameters": {
            "contrast_value": {
              "value": 0.4
            }
          }
        }
      }
    },
    "ocr_results": [
      {
        "text": "Chinese Cinderella",
        "confidence": 0.9947171857629314
      },
      {
        "text": "3",
        "confidence": 0.9652753625360369
      }
    ],
    "score": 18.8701847062688
  },
  "11.jpg": {
    "config_dict": {
      "steps": {
        "image_rotation": {
          "enabled": true,
          "parameters": {
            "rotation_angle": {
              "value": 136.0
            }
          }
        },
        "shadow_removal": {
          "enabled": true,
          "parameters": {
            "shadow_kernel_size": {
              "value": 6.0
            },
            "shadow_median_blur": {
              "value": 20.0
            }
          }
        },
        "color_clahe": {
          "enabled": true,
          "parameters": {
            "clahe_clip_limit": {
              "value": 0.1
            }
          }
        },
        "brightness_adjustment": {
          "enabled": true,
          "parameters": {
            "brightness_value": {
              "value": -12.0
            }
          }
        },
        "contrast_adjustment": {
          "enabled": true,
          "parameters": {
            "contrast_value": {
              "value": 0.6
            }
          }
        }
      }
    },
    "ocr_results": [
      {
        "text": "ANN RINALD",
        "confidence": 0.9964553279832898
      },
      {
        "text": "ML",
        "confidence": 0.9879437127786027
      },
      {
        "text": "n",
        "confidence": 0.9622710840858417
      },
      {
        "text": "Quilt",
        "confidence": 0.9745099220442626
      },
      {
        "text": "Harcourt",
        "confidence": 0.9393880347816591
      }
    ],
    "score": 25.29036567795053
  },
  "12.jpg": {
    "config_dict": {
      "steps": {
        "image_rotation": {
          "enabled": true,
          "parameters": {
            "rotation_angle": {
              "value": 220.0
            }
          }
        },
        "shadow_removal": {
          "enabled": true,
          "parameters": {
            "shadow_kernel_size": {
              "value": 14.0
            },
            "shadow_median_blur": {
              "value": 13.0
            }
          }
        },
        "color_clahe": {
          "enabled": true,
          "parameters": {
            "clahe_clip_limit": {
              "value": 2.7
            }
          }
        },
        "brightness_adjustment": {
          "enabled": true,
          "parameters": {
            "brightness_value": {
              "value": 21.0
            }
          }
        },
        "contrast_adjustment": {
          "enabled": true,
          "parameters": {
            "contrast_value": {
              "value": 0.5
            }
          }
        }
      }
    },
    "ocr_results": [
      {
        "text": "Emperor",
        "confidence": 0.9933557592947418
      },
      {
        "text": "Betsy",
        "confidence": 0.9999064902096317
      },
      {
        "text": "Rabin",
        "confidence": 0.9832533631951426
      }
    ],
    "score": 16.869289582087067
  },
  "13.jpg": {
    "config_dict": {
      "steps": {
        "image_rotation": {
          "enabled": true,
          "parameters": {
            "rotation_angle": {
              "value": 174.0
            }
          }
        },
        "shadow_removal": {
          "enabled": true,
          "parameters": {
            "shadow_kernel_size": {
              "value": 7.0
            },
            "shadow_median_blur": {
              "value": 13.0
            }
          }
        },
        "color_clahe": {
          "enabled": true,
          "parameters": {
            "clahe_clip_limit": {
              "value": 2.4
            }
          }
        },
        "brightness_adjustment": {
          "enabled": true,
          "parameters": {
            "brightness_value": {
              "value": -2.0
            }
          }
        },
        "contrast_adjustment": {
          "enabled": true,
          "parameters": {
            "contrast_value": {
              "value": 0.6
            }
          }
        }
      }
    },
    "ocr_results": [
      {
        "text": "Wolf by the Ears",
        "confidence": 0.9625130358554195
      },
      {
        "text": "Rinaldi",
        "confidence": 0.9997432552765745
      }
    ],
    "score": 22.39841136062273
  },
  "14.jpg": {
    "config_dict": {
      "steps": {
        "image_rotation": {
          "enabled": true,
          "parameters": {
            "rotation_angle": {
              "value": 178.0
            }
          }
        },
        "shadow_removal": {
          "enabled": true,
          "parameters": {
            "shadow_kernel_size": {
              "value": 11.0
            },
            "shadow_median_blur": {
              "value": 20.0
            }
          }
        },
        "color_clahe": {
          "enabled": true,
          "parameters": {
            "clahe_clip_limit": {
              "value": 1.6
            }
          }
        },
        "brightness_adjustment": {
          "enabled": true,
          "parameters": {
            "brightness_value": {
              "value": 26.0
            }
          }
        },
        "contrast_adjustment": {
          "enabled": true,
          "parameters": {
            "contrast_value": {
              "value": 0.4
            }
          }
        }
      }
    },
    "ocr_results": [
      {
        "text": "JOHNNY TREMAIN",
        "confidence": 0.9863034305339988
      },
      {
        "text": "1",
        "confidence": 0.6217087683858757
      },
      {
        "text": "1",
        "confidence": 0.9636339038681996
      }
    ],
    "score": 15.393590699730058
  },
  "15.jpg": {
    "config_dict": {
      "steps": {
        "image_rotation": {
          "enabled": true,
          "parameters": {
            "rotation_angle": {
              "value": 144.0
            }
          }
        },
        "shadow_removal": {
          "enabled": true,
          "parameters": {
            "shadow_kernel_size": {
              "value": 6.0
            },
            "shadow_median_blur": {
              "value": 20.0
            }
          }
        },
        "color_clahe": {
          "enabled": true,
          "parameters": {
            "clahe_clip_limit": {
              "value": 0.2
            }
          }
        },
        "brightness_adjustment": {
          "enabled": true,
          "parameters": {
            "brightness_value": {
              "value": -14.0
            }
          }
        },
        "contrast_adjustment": {
          "enabled": true,
          "parameters": {
            "contrast_value": {
              "value": 0.6
            }
          }
        }
      }
    },
    "ocr_results": [
      {
        "text": "SOLDIERS HEART",
        "confidence": 0.992734785642418
      },
      {
        "text": "0",
        "confidence": 0.9402622162990646
      },
      {
        "text": "GARY PAULSEN",
        "confidence": 0.9947937478242318
      }
    ],
    "score": 26.776074189183696
  },
  "16.jpg": {
    "config_dict": {
      "steps": {
        "image_rotation": {
          "enabled": true,
          "parameters": {
            "rotation_angle": {
              "value": 165.0
            }
          }
        },
        "shadow_removal": {
          "enabled": true,
          "parameters": {
            "shadow_kernel_size": {
              "value": 8.0
            },
            "shadow_median_blur": {
              "value": 24.0
            }
          }
        },
        "color_clahe": {
          "enabled": true,
          "parameters": {
            "clahe_clip_limit": {
              "value": 1.3
            }
          }
        },
        "brightness_adjustment": {
          "enabled": true,
          "parameters": {
            "brightness_value": {
              "value": 10.0
            }
          }
        },
        "contrast_adjustment": {
          "enabled": true,
          "parameters": {
            "contrast_value": {
              "value": 0.6
            }
          }
        }
      }
    },
    "ocr_results": [
      {
        "text": "SThe STrue Confessions gf\" Chartotte",
        "confidence": 0.54061243180703
      },
      {
        "text": "Fvi",
        "confidence": 0.7661351386831812
      },
      {
        "text": "7",
        "confidence": 0.573547826699329
      }
    ],
    "score": 22.334000787801955
  },
  "17.jpg": {
    "config_dict": {
      "steps": {
        "image_rotation": {
          "enabled": true,
          "parameters": {
            "rotation_angle": {
              "value": 270.0
            }
          }
        },
        "shadow_removal": {
          "enabled": true,
          "parameters": {
            "shadow_kernel_size": {
              "value": 18.0
            },
            "shadow_median_blur": {
              "value": 4.0
            }
          }
        },
        "color_clahe": {
          "enabled": true,
          "parameters": {
            "clahe_clip_limit": {
              "value": 2.7
            }
          }
        },
        "brightness_adjustment": {
          "enabled": true,
          "parameters": {
            "brightness_value": {
              "value": 43.0
            }
          }
        },
        "contrast_adjustment": {
          "enabled": true,
          "parameters": {
            "contrast_value": {
              "value": 1.0
            }
          }
        }
      }
    },
    "ocr_results": [
      {
        "text": "GERMAN SOLDIER",
        "confidence": 0.96886550605481
      },
      {
        "text": "SuMMER",
        "confidence": 0.9738186407845956
      },
      {
        "text": "1",
        "confidence": 0.14814333273048508
      }
    ],
    "score": 19.5551722622054
  },
  "18.jpg": {
    "config_dict": {
      "steps": {
        "image_rotation": {
          "enabled": true,
          "parameters": {
            "rotation_angle": {
              "value": 265.0
            }
          }
        },
        "shadow_removal": {
          "enabled": true,
          "parameters": {
            "shadow_kernel_size": {
              "value": 20.0
            },
            "shadow_median_blur": {
              "value": 13.0
            }
          }
        },
        "color_clahe": {
          "enabled": true,
          "parameters": {
            "clahe_clip_limit": {
              "value": 3.0
            }
          }
        },
        "brightness_adjustment": {
          "enabled": true,
          "parameters": {
            "brightness_value": {
              "value": 31.0
            }
          }
        },
        "contrast_adjustment": {
          "enabled": true,
          "parameters": {
            "contrast_value": {
              "value": 0.7
            }
          }
        }
      }
    },
    "ocr_results": [
      {
        "text": "DANIEL HALF HUMAN",
        "confidence": 0.9418155384712475
      },
      {
        "text": "CHOTJEWITZ",
        "confidence": 0.9950168129746879
      }
    ],
    "score": 25.961032283758087
  },
  "19.jpg": {
    "config_dict": {
      "steps": {
        "image_rotation": {
          "enabled": true,
          "parameters": {
            "rotation_angle": {
              "value": 122.0
            }
          }
        },
        "shadow_removal": {
          "enabled": true,
          "parameters": {
            "shadow_kernel_size": {
              "value": 3.0
            },
            "shadow_median_blur": {
              "value": 22.0
            }
          }
        },
        "color_clahe": {
          "enabled": true,
          "parameters": {
            "clahe_clip_limit": {
              "value": 0.4
            }
          }
        },
        "brightness_adjustment": {
          "enabled": true,
          "parameters": {
            "brightness_value": {
              "value": 10.0
            }
          }
        },
        "contrast_adjustment": {
          "enabled": true,
          "parameters": {
            "contrast_value": {
              "value": 0.6
            }
          }
        }
      }
    },
    "ocr_results": [
      {
        "text": "SARAH BISHOP",
        "confidence": 0.9864281829082624
      },
      {
        "text": "SCOTT ODELL",
        "confidence": 0.9717625083599962
      }
    ],
    "score": 22.526525786859107
  },
  "2.jpg": {
    "config_dict": {
      "steps": {
        "image_rotation": {
          "enabled": true,
          "parameters": {
            "rotation_angle": {
              "value": 250.0
            }
          }
        },
        "shadow_removal": {
          "enabled": true,
          "parameters": {
            "shadow_kernel_size": {
              "value": 21.0
            },
            "shadow_median_blur": {
              "value": 12.0
            }
          }
        },
        "color_clahe": {
          "enabled": true,
          "parameters": {
            "clahe_clip_limit": {
              "value": 2.9
            }
          }
        },
        "brightness_adjustment": {
          "enabled": true,
          "parameters": {
            "brightness_value": {
              "value": 27.0
            }
          }
        },
        "contrast_adjustment": {
          "enabled": true,
          "parameters": {
            "contrast_value": {
              "value": 0.7
            }
          }
        }
      }
    },
    "ocr_results": [
      {
        "text": "arcoun",
        "confidence": 0.8261918801321365
      },
      {
        "text": "Rever €",
        "confidence": 0.8358634976825203
      },
      {
        "text": "965",
        "confidence": 0.3223513960838318
      },
      {
        "text": "3",
        "confidence": 0.4825146832559426
      },
      {
        "text": "RINALDI",
        "confidence": 0.9852589588753975
      },
      {
        "text": "ANN",
        "confidence": 0.9999730892719857
      }
    ],
    "score": 22.15449661602164
  },
  "20.jpg": {
    "config_dict": {
      "steps": {
        "image_rotation": {
          "enabled": true,
          "parameters": {
            "rotation_angle": {
              "value": 215.0
            }
          }
        },
        "shadow_removal": {
          "enabled": true,
          "parameters": {
            "shadow_kernel_size": {
              "value": 11.0
            },
            "shadow_median_blur": {
              "value": 14.0
            }
          }
        },
        "color_clahe": {
          "enabled": true,
          "parameters": {
            "clahe_clip_limit": {
              "value": 2.5
            }
          }
        },
        "brightness_adjustment": {
          "enabled": true,
          "parameters": {
            "brightness_value": {
              "value": 22.0
            }
          }
        },
        "contrast_adjustment": {
          "enabled": true,
          "parameters": {
            "contrast_value": {
              "value": 0.5
            }
          }
        }
      }
    },
    "ocr_results": [
      {
        "text": "spcak",
        "confidence": 0.8719247158765755
      },
      {
        "text": "Civil War",
        "confidence": 0.9323507185875908
      },
      {
        "text": "Gyvys",
        "confidence": 0.9138753472088846
      },
      {
        "text": "7",
        "confidence": 0.6177625710756196
      },
      {
        "text": "8",
        "confidence": 0.9726463520804742
      },
      {
        "text": "~BRENAMAN",
        "confidence": 0.9505786224968734
      }
    ],
    "score": 27.46577330834357
  },
  "21.jpg": {
    "config_dict": {
      "steps": {
        "image_rotation": {
          "enabled": true,
          "parameters": {
            "rotation_angle": {
              "value": 236.0
            }
          }
        },
        "shadow_removal": {
          "enabled": true,
          "parameters": {
            "shadow_kernel_size": {
              "value": 12.0
            },
            "shadow_median_blur": {
              "value": 16.0
            }
          }
        },
        "color_clahe": {
          "enabled": true,
          "parameters": {
            "clahe_clip_limit": {
              "value": 2.3
            }
          }
        },
        "brightness_adjustment": {
          "enabled": true,
          "parameters": {
            "brightness_value": {
              "value": 8.0
            }
          }
        },
        "contrast_adjustment": {
          "enabled": true,
          "parameters": {
            "contrast_value": {
              "value": 1.0
            }
          }
        }
      }
    },
    "ocr_results": [
      {
        "text": "BREAD",
        "confidence": 0.9809426435421522
      },
      {
        "text": "WARM",
        "confidence": 0.975427508354187
      },
      {
        "text": "RaiNED",
        "confidence": 0.7881773116911018
      },
      {
        "text": "Lyon",
        "confidence": 0.9053496718406677
      },
      {
        "text": "1",
        "confidence": 0.896153498326612
      },
      {
        "text": "Hoskowitz SWFET",
        "confidence": 0.6493055521040741
      }
    ],
    "score": 27.792622588524516
  },
  "22.jpg": {
    "config_dict": {
      "steps": {
        "image_rotation": {
          "enabled": true,
          "parameters": {
            "rotation_angle": {
              "value": 221.0
            }
          }
        },
        "shadow_removal": {
          "enabled": true,
          "parameters": {
            "shadow_kernel_size": {
              "value": 15.0
            },
            "shadow_median_blur": {
              "value": 12.0
            }
          }
        },
        "color_clahe": {
          "enabled": true,
          "parameters": {
            "clahe_clip_limit": {
              "value": 2.9
            }
          }
        },
        "brightness_adjustment": {
          "enabled": true,
          "parameters": {
            "brightness_value": {
              "value": 30.0
            }
          }
        },
        "contrast_adjustment": {
          "enabled": true,
          "parameters": {
            "contrast_value": {
              "value": 0.6
            }
          }
        }
      }
    },
    "ocr_results": [
      {
        "text": "thE DAWN OF JIM CROW",
        "confidence": 0.38931692015742686
      },
      {
        "text": "QKV NOIL",
        "confidence": 0.5700384431732709
      },
      {
        "text": "RECONSTRUCT",
        "confidence": 0.9403368242004223
      },
      {
        "text": "RISING",
        "confidence": 0.9979139842865011
      },
      {
        "text": "SKYL",
        "confidence": 0.9299233555793762
      },
      {
        "text": "DARK",
        "confidence": 0.9810764193534851
      },
      {
        "text": "Bolden",
        "confidence": 0.99974926060905
      },
      {
        "text": "GATES",
        "confidence": 0.9339648433504765
      },
      {
        "text": "Focus",
        "confidence": 0.8485305672747002
      }
    ],
    "score": 51.23280663696998
  },
  "23.jpg": {
    "config_dict": {
      "steps": {
        "image_rotation": {
          "enabled": true,
          "parameters": {
            "rotation_angle": {
              "value": 170.0
            }
          }
        },
        "shadow_removal": {
          "enabled": true,
          "parameters": {
            "shadow_kernel_size": {
              "value": 8.0
            },
            "shadow_median_blur": {
              "value": 23.0
            }
          }
        },
        "color_clahe": {
          "enabled": true,
          "parameters": {
            "clahe_clip_limit": {
              "value": 1.0
            }
          }
        },
        "brightness_adjustment": {
          "enabled": true,
          "parameters": {
            "brightness_value": {
              "value": 1.0
            }
          }
        },
        "contrast_adjustment": {
          "enabled": true,
          "parameters": {
            "contrast_value": {
              "value": 1.0
            }
          }
        }
      }
    },
    "ocr_results": [
      {
        "text": "8",
        "confidence": 0.9327697306321738
      },
      {
        "text": "DREAM",
        "confidence": 0.9565250308283654
      },
      {
        "text": "the",
        "confidence": 0.9915824455979869
      },
      {
        "text": "Q0)",
        "confidence": 0.7468810989847029
      },
      {
        "text": "ROBINSON",
        "confidence": 0.9903338817293728
      }
    ],
    "score": 18.85345657235705
  },
  "24.jpg": {
    "config_dict": {
      "steps": {
        "image_rotation": {
          "enabled": true,
          "parameters": {
            "rotation_angle": {
              "value": 162.0
            }
          }
        },
        "shadow_removal": {
          "enabled": true,
          "parameters": {
            "shadow_kernel_size": {
              "value": 5.0
            },
            "shadow_median_blur": {
              "value": 24.0
            }
          }
        },
        "color_clahe": {
          "enabled": true,
          "parameters": {
            "clahe_clip_limit": {
              "value": 0.4
            }
          }
        },
        "brightness_adjustment": {
          "enabled": true,
          "parameters": {
            "brightness_value": {
              "value": 7.0
            }
          }
        },
        "contrast_adjustment": {
          "enabled": true,
          "parameters": {
            "contrast_value": {
              "value": 0.9
            }
          }
        }
      }
    },
    "ocr_results": [
      {
        "text": "HOME % the BRAVE",
        "confidence": 0.8885609865468107
      },
      {
        "text": "APPLEGATE",
        "confidence": 0.9483911545095295
      }
    ],
    "score": 22.752496175334734
  },
  "25.jpg": {
    "config_dict": {
      "steps": {
        "image_rotation": {
          "enabled": true,
          "parameters": {
            "rotation_angle": {
              "value": 221.0
            }
          }
        },
        "shadow_removal": {
          "enabled": true,
          "parameters": {
            "shadow_kernel_size": {
              "value": 15.0
            },
            "shadow_median_blur": {
              "value": 12.0
            }
          }
        },
        "color_clahe": {
          "enabled": true,
          "parameters": {
            "clahe_clip_limit": {
              "value": 2.9
            }
          }
        },
        "brightness_adjustment": {
          "enabled": true,
          "parameters": {
            "brightness_value": {
              "value": 30.0
            }
          }
        },
        "contrast_adjustment": {
          "enabled": true,
          "parameters": {
            "contrast_value": {
              "value": 0.6
            }
          }
        }
      }
    },
    "ocr_results": [
      {
        "text": "3",
        "confidence": 0.6856259653943653
      },
      {
        "text": "ANGELS",
        "confidence": 0.9988090080092139
      },
      {
        "text": "WITH THE MIGHJ OF",
        "confidence": 0.7818303866565717
      }
    ],
    "score": 19.969596586611367
  },
  "26.jpg": {
    "config_dict": {
      "steps": {
        "image_rotation": {
          "enabled": true,
          "parameters": {
            "rotation_angle": {
              "value": 263.0
            }
          }
        },
        "shadow_removal": {
          "enabled": true,
          "parameters": {
            "shadow_kernel_size": {
              "value": 12.0
            },
            "shadow_median_blur": {
              "value": 16.0
            }
          }
        },
        "color_clahe": {
          "enabled": true,
          "parameters": {
            "clahe_clip_limit": {
              "value": 1.1
            }
          }
        },
        "brightness_adjustment": {
          "enabled": true,
          "parameters": {
            "brightness_value": {
              "value": -16.0
            }
          }
        },
        "contrast_adjustment": {
          "enabled": true,
          "parameters": {
            "contrast_value": {
              "value": 0.5
            }
          }
        }
      }
    },
    "ocr_results": [
      {
        "text": "1",
        "confidence": 0.8941047515897118
      },
      {
        "text": "Manzanar",
        "confidence": 0.9519180690722163
      },
      {
        "text": "Houston",
        "confidence": 0.9996526821217325
      }
    ],
    "score": 15.50701807901957
  },
  "27.jpg": {
    "config_dict": {
      "steps": {
        "image_rotation": {
          "enabled": true,
          "parameters": {
            "rotation_angle": {
              "value": 160.0
            }
          }
        },
        "shadow_removal": {
          "enabled": true,
          "parameters": {
            "shadow_kernel_size": {
              "value": 4.0
            },
            "shadow_median_blur": {
              "value": 27.0
            }
          }
        },
        "color_clahe": {
          "enabled": true,
          "parameters": {
            "clahe_clip_limit": {
              "value": 1.1
            }
          }
        },
        "brightness_adjustment": {
          "enabled": true,
          "parameters": {
            "brightness_value": {
              "value": 43.0
            }
          }
        },
        "contrast_adjustment": {
          "enabled": true,
          "parameters": {
            "contrast_value": {
              "value": 0.6
            }
          }
        }
      }
    },
    "ocr_results": [
      {
        "text": "900u 1 S J00 0 JG",
        "confidence": 0.17173883781565957
      },
      {
        "text": "5",
        "confidence": 0.5949348876556684
      }
    ],
    "score": 3.514495130521881
  },
  "28.jpg": {
    "config_dict": {
      "steps": {
        "image_rotation": {
          "enabled": true,
          "parameters": {
            "rotation_angle": {
              "value": 270.0
            }
          }
        },
        "shadow_removal": {
          "enabled": true,
          "parameters": {
            "shadow_kernel_size": {
              "value": 18.0
            },
            "shadow_median_blur": {
              "value": 11.0
            }
          }
        },
        "color_clahe": {
          "enabled": true,
          "parameters": {
            "clahe_clip_limit": {
              "value": 3.8
            }
          }
        },
        "brightness_adjustment": {
          "enabled": true,
          "parameters": {
            "brightness_value": {
              "value": 50.0
            }
          }
        },
        "contrast_adjustment": {
          "enabled": true,
          "parameters": {
            "contrast_value": {
              "value": 0.7
            }
          }
        }
      }
    },
    "ocr_results": [
      {
        "text": "1",
        "confidence": 0.24277259502401094
      },
      {
        "text": "BOUT aook $ Lil E",
        "confidence": 0.43851309942190037
      },
      {
        "text": "LITCHAT",
        "confidence": 0.46305980885043885
      }
    ],
    "score": 10.93891394714939
  },
  "29.jpg": {
    "config_dict": {
      "steps": {
        "image_rotation": {
          "enabled": true,
          "parameters": {
            "rotation_angle": {
              "value": 161.0
            }
          }
        },
        "shadow_removal": {
          "enabled": true,
          "parameters": {
            "shadow_kernel_size": {
              "value": 5.0
            },
            "shadow_median_blur": {
              "value": 28.0
            }
          }
        },
        "color_clahe": {
          "enabled": true,
          "parameters": {
            "clahe_clip_limit": {
              "value": 1.7
            }
          }
        },
        "brightness_adjustment": {
          "enabled": true,
          "parameters": {
            "brightness_value": {
              "value": 41.0
            }
          }
        },
        "contrast_adjustment": {
          "enabled": true,
          "parameters": {
            "contrast_value": {
              "value": 0.6
            }
          }
        }
      }
    },
    "ocr_results": [
      {
        "text": "ABOOK",
        "confidence": 0.8892596226069149
      },
      {
        "text": "borrowved phrases",
        "confidence": 0.8808241717255003
      },
      {
        "text": "Ihe game",
        "confidence": 0.7742592931437337
      }
    ],
    "score": 25.61438337751795
  },
  "3.jpg": {
    "config_dict": {
      "steps": {
        "image_rotation": {
          "enabled": true,
          "parameters": {
            "rotation_angle": {
              "value": 129.0
            }
          }
        },
        "shadow_removal": {
          "enabled": true,
          "parameters": {
            "shadow_kernel_size": {
              "value": 4.0
            },
            "shadow_median_blur": {
              "value": 18.0
            }
          }
        },
        "color_clahe": {
          "enabled": true,
          "parameters": {
            "clahe_clip_limit": {
              "value": 1.4
            }
          }
        },
        "brightness_adjustment": {
          "enabled": true,
          "parameters": {
            "brightness_value": {
              "value": 0.0
            }
          }
        },
        "contrast_adjustment": {
          "enabled": true,
          "parameters": {
            "contrast_value": {
              "value": 0.4
            }
          }
        }
      }
    },
    "ocr_results": [
      {
        "text": "Hang",
        "confidence": 0.7379775643348694
      },
      {
        "text": "Thousand",
        "confidence": 0.9770528006220447
      },
      {
        "text": "ANN",
        "confidence": 0.9991735889745519
      },
      {
        "text": "RINAL DI",
        "confidence": 0.8514500446963219
      },
      {
        "text": "5",
        "confidence": 0.941176091751462
      },
      {
        "text": "Trees with Ribbons",
        "confidence": 0.9934252940072349
      }
    ],
    "score": 39.40028517069176
  },
  "4.jpg": {
    "config_dict": {
      "steps": {
        "image_rotation": {
          "enabled": true,
          "parameters": {
            "rotation_angle": {
              "value": 270.0
            }
          }
        },
        "shadow_removal": {
          "enabled": true,
          "parameters": {
            "shadow_kernel_size": {
              "value": 7.0
            },
            "shadow_median_blur": {
              "value": 17.0
            }
          }
        },
        "color_clahe": {
          "enabled": true,
          "parameters": {
            "clahe_clip_limit": {
              "value": 2.3
            }
          }
        },
        "brightness_adjustment": {
          "enabled": true,
          "parameters": {
            "brightness_value": {
              "value": 49.0
            }
          }
        },
        "contrast_adjustment": {
          "enabled": true,
          "parameters": {
            "contrast_value": {
              "value": 0.6
            }
          }
        }
      }
    },
    "ocr_results": [
      {
        "text": "ANNN RINALDI",
        "confidence": 0.9318386463847751
      }
    ],
    "score": 11.182063756617302
  },
  "5.jpg": {
    "config_dict": {
      "steps": {
        "image_rotation": {
          "enabled": true,
          "parameters": {
            "rotation_angle": {
              "value": 213.0
            }
          }
        },
        "shadow_removal": {
          "enabled": true,
          "parameters": {
            "shadow_kernel_size": {
              "value": 11.0
            },
            "shadow_median_blur": {
              "value": 16.0
            }
          }
        },
        "color_clahe": {
          "enabled": true,
          "parameters": {
            "clahe_clip_limit": {
              "value": 2.5
            }
          }
        },
        "brightness_adjustment": {
          "enabled": true,
          "parameters": {
            "brightness_value": {
              "value": 20.0
            }
          }
        },
        "contrast_adjustment": {
          "enabled": true,
          "parameters": {
            "contrast_value": {
              "value": 0.6
            }
          }
        }
      }
    },
    "ocr_results": [
      {
        "text": "Ann Rinaldi",
        "confidence": 0.8607198873326002
      },
      {
        "text": "THE SECOND BEND IN THE RIVER",
        "confidence": 0.8917670221913514
      },
      {
        "text": "FON SONATURE",
        "confidence": 0.4584895279469867
      }
    ],
    "score": 39.939269717380284
  },
  "6.jpg": {
    "config_dict": {
      "steps": {
        "image_rotation": {
          "enabled": true,
          "parameters": {
            "rotation_angle": {
              "value": 164.0
            }
          }
        },
        "shadow_removal": {
          "enabled": true,
          "parameters": {
            "shadow_kernel_size": {
              "value": 3.0
            },
            "shadow_median_blur": {
              "value": 19.0
            }
          }
        },
        "color_clahe": {
          "enabled": true,
          "parameters": {
            "clahe_clip_limit": {
              "value": 2.2
            }
          }
        },
        "brightness_adjustment": {
          "enabled": true,
          "parameters": {
            "brightness_value": {
              "value": 12.0
            }
          }
        },
        "contrast_adjustment": {
          "enabled": true,
          "parameters": {
            "contrast_value": {
              "value": 0.7
            }
          }
        }
      }
    },
    "ocr_results": [
      {
        "text": "William Lavender",
        "confidence": 0.9725669259429109
      },
      {
        "text": "JUST JANE",
        "confidence": 0.9128124426590672
      },
      {
        "text": "5",
        "confidence": 0.9905048581893006
      }
    ],
    "score": 24.76688765720748
  },
  "7.jpg": {
    "config_dict": {
      "steps": {
        "image_rotation": {
          "enabled": true,
          "parameters": {
            "rotation_angle": {
              "value": 158.0
            }
          }
        },
        "shadow_removal": {
          "enabled": true,
          "parameters": {
            "shadow_kernel_size": {
              "value": 3.0
            },
            "shadow_median_blur": {
              "value": 22.0
            }
          }
        },
        "color_clahe": {
          "enabled": true,
          "parameters": {
            "clahe_clip_limit": {
              "value": 1.7
            }
          }
        },
        "brightness_adjustment": {
          "enabled": true,
          "parameters": {
            "brightness_value": {
              "value": 12.0
            }
          }
        },
        "contrast_adjustment": {
          "enabled": true,
          "parameters": {
            "contrast_value": {
              "value": 0.4
            }
          }
        }
      }
    },
    "ocr_results": [
      {
        "text": "BREA K",
        "confidence": 0.7421209371085747
      },
      {
        "text": "V",
        "confidence": 0.8672352881949088
      },
      {
        "text": "ANN",
        "confidence": 0.9999804535792165
      },
      {
        "text": "RINALD [",
        "confidence": 0.9597811163919823
      },
      {
        "text": "8",
        "confidence": 0.8392865437005561
      },
      {
        "text": "with CHARity",
        "confidence": 0.6541782642936873
      }
    ],
    "score": 24.687576917944668
  },
  "8.jpg": {
    "config_dict": {
      "steps": {
        "image_rotation": {
          "enabled": true,
          "parameters": {
            "rotation_angle": {
              "value": 95.0
            }
          }
        },
        "shadow_removal": {
          "enabled": true,
          "parameters": {
            "shadow_kernel_size": {
              "value": 7.0
            },
            "shadow_median_blur": {
              "value": 10.0
            }
          }
        },
        "color_clahe": {
          "enabled": true,
          "parameters": {
            "clahe_clip_limit": {
              "value": 2.6
            }
          }
        },
        "brightness_adjustment": {
          "enabled": true,
          "parameters": {
            "brightness_value": {
              "value": 20.0
            }
          }
        },
        "contrast_adjustment": {
          "enabled": true,
          "parameters": {
            "contrast_value": {
              "value": 1.1
            }
          }
        }
      }
    },
    "ocr_results": [
      {
        "text": "FINISHING BECCA",
        "confidence": 0.9836464250974393
      },
      {
        "text": "1",
        "confidence": 0.9170495822696125
      },
      {
        "text": "CU!",
        "confidence": 0.39799091923453417
      }
    ],
    "score": 16.865718716434802
  },
  "9.jpg": {
    "config_dict": {
      "steps": {
        "image_rotation": {
          "enabled": true,
          "parameters": {
            "rotation_angle": {
              "value": 193.0
            }
          }
        },
        "shadow_removal": {
          "enabled": true,
          "parameters": {
            "shadow_kernel_size": {
              "value": 9.0
            },
            "shadow_median_blur": {
              "value": 17.0
            }
          }
        },
        "color_clahe": {
          "enabled": true,
          "parameters": {
            "clahe_clip_limit": {
              "value": 2.6
            }
          }
        },
        "brightness_adjustment": {
          "enabled": true,
          "parameters": {
            "brightness_value": {
              "value": 23.0
            }
          }
        },
        "contrast_adjustment": {
          "enabled": true,
          "parameters": {
            "contrast_value": {
              "value": 0.8
            }
          }
        }
      }
    },
    "ocr_results": [
      {
        "text": "BEYOND THE BURNING",
        "confidence": 0.8110505397377513
      }
    ],
    "score": 14.598909715279524
  }
}